pylpg/__init__.py
pylpg/lpg_execution.py
pylpg/lpgdata.py
pylpg/lpgpythonbindings.py
test/__init__.py
test/test_pylpg.py
pyloadprofilegenerator-0.1.1.dist-info/LICENSE
pyloadprofilegenerator-0.1.1.dist-info/METADATA
pyloadprofilegenerator-0.1.1.dist-info/WHEEL
pyloadprofilegenerator-0.1.1.dist-info/top_level.txt
pyloadprofilegenerator-0.1.1.dist-info/RECORD
