Metadata-Version: 2.1
Name: pyloadprofilegenerator
Version: 0.1.1
Summary: Python Bindings for the LoadProfileGenerator
Home-page: https://github.com/FZJ-IEK3-VSA/pylpg
Author: Noah Pflugradt
Author-email: n.pflugradt@fz-juelich.de
Keywords: buildings,thermal load,electricity load
Classifier: Development Status :: 3 - Alpha
Classifier: Intended Audience :: End Users/Desktop
Classifier: Intended Audience :: Science/Research
Classifier: License :: OSI Approved :: MIT License
Classifier: Natural Language :: English
Classifier: Operating System :: OS Independent
Classifier: Programming Language :: Python
Classifier: Programming Language :: Python :: 3
Classifier: Programming Language :: Python :: 3.10
Classifier: Topic :: Scientific/Engineering
Classifier: Topic :: Software Development :: Libraries :: Python Modules
License-File: LICENSE
Requires-Dist: setuptools
Requires-Dist: requests
Requires-Dist: dataclasses-json
Requires-Dist: pandas
Requires-Dist: numpy
